garmin_mcp_demo/__init__.py
garmin_mcp_demo-0.1.0.dist-info/METADATA
garmin_mcp_demo-0.1.0.dist-info/WHEEL
garmin_mcp_demo-0.1.0.dist-info/entry_points.txt
garmin_mcp_demo-0.1.0.dist-info/RECORD
