Metadata-Version: 2.4
Name: garmin-mcp-demo
Version: 0.1.0
Summary: Add your description here
Author-email: "J.M.Bai" <bai13369472336@163.com>
Requires-Python: >=3.13
Requires-Dist: mcp[cli]>=1.9.3
